camelx/__init__.py
camelx/camelx.py
camelx/camelx_cy.c
camelx/tests/__init__.py
camelx/tests/test_docs.py
camelx/tests/test_general.py
camelx-0.0.2.dist-info/LICENSE
camelx-0.0.2.dist-info/METADATA
camelx-0.0.2.dist-info/WHEEL
camelx-0.0.2.dist-info/top_level.txt
camelx-0.0.2.dist-info/RECORD
