Metadata-Version: 2.1
Name: camelx
Version: 0.0.2
Summary: Python serialization for adults
Home-page: https://github.com/vzool/camelx
Author: Eevee (Lexy Munroe)
Author-email: "Eevee (Lexy Munroe)" <eevee.camel@veekun.com>
Maintainer: Abdelaziz Elrashed Elshaikh Mohamed
Maintainer-email: Abdelaziz Elrashed Elshaikh Mohamed <aeemh.sdn@gmail.com>
Project-URL: Homepage, https://github.com/vzool/camelx
Project-URL: Issues, https://github.com/vzool/camelx/issues
Classifier: Development Status :: 2 - Pre-Alpha
Classifier: Intended Audience :: Developers
Classifier: License :: OSI Approved :: ISC License (ISCL)
Classifier: Programming Language :: Python :: 2
Classifier: Programming Language :: Python :: 2.7
Classifier: Programming Language :: Python :: 3
Classifier: Programming Language :: Python :: 3.2
Classifier: Programming Language :: Python :: 3.3
Classifier: Programming Language :: Python :: 3.4
Classifier: Programming Language :: Python :: 3.5
Requires: pyyaml
License-File: LICENSE
Requires-Dist: pyyaml
